Metadata-Version: 1.0
Name: jon-dist-prob
Version: 0.1
Summary: Gaussian and Binomial distributions
Home-page: UNKNOWN
Author: Mukhammad Khalimudin
Author-email: khalimudin@gmail.com
License: UNKNOWN
Platform: UNKNOWN
